aec_audio_processing/__init__.py
aec_audio_processing/_audio_processing.py
aec_audio_processing/_version.py
aec_audio_processing/_webrtc_audio_processing.cpython-312-darwin.so
aec_audio_processing/audio_processing.i
aec_audio_processing/audio_processing.py
aec_audio_processing/audio_processing_module.cpp
aec_audio_processing/audio_processing_module.h
aec_audio_processing/audio_processing_wrap.cpp
aec_audio_processing/loader.py
aec_audio_processing/webrtc_audio_processing.py
aec_audio_processing/files/__init__.py
aec_audio_processing/files/libwebrtc-audio-processing-2.dylib
aec_audio_processing-1.0.0.dev6.dist-info/licenses/LICENSE
aec_audio_processing-1.0.0.dev6.dist-info/METADATA
aec_audio_processing-1.0.0.dev6.dist-info/WHEEL
aec_audio_processing-1.0.0.dev6.dist-info/top_level.txt
aec_audio_processing-1.0.0.dev6.dist-info/RECORD
